sphinx_carousel/__init__.py
sphinx_carousel/_static/bootstrap-carousel.min.css
sphinx_carousel/_static/bootstrap-carousel.min.js
sphinx_carousel/_static/carousel-custom.css_t
sphinx_carousel/carousel.py
sphinx_carousel/directives.py
sphinx_carousel/nodes.py
sphinx_carousel-1.1.0.dist-info/COPYING
sphinx_carousel-1.1.0.dist-info/LICENSE
sphinx_carousel-1.1.0.dist-info/WHEEL
sphinx_carousel-1.1.0.dist-info/METADATA
sphinx_carousel-1.1.0.dist-info/RECORD
